py2gmsh/Entity.py
py2gmsh/Field.py
py2gmsh/Mesh.py
py2gmsh/Options.py
py2gmsh/__init__.py
py2gmsh-4.2.3.1.dist-info/METADATA
py2gmsh-4.2.3.1.dist-info/RECORD
py2gmsh-4.2.3.1.dist-info/WHEEL
py2gmsh-4.2.3.1.dist-info/top_level.txt
