Metadata-Version: 2.1
Name: py2gmsh
Version: 4.2.3.1
Summary: Python wrappers to gmsh files with object-oriented syntax
Home-page: https://github.com/tridelat/py2gmsh
Author: Tristan de Lataillade
Author-email: delataillade.tristan@gmail.com
License: UNKNOWN
Download-URL: https://github.com/tridelat/py2gmsh/tarball/v4.2.3.1
Keywords: gmsh,wrapper,mesh,python,api
Platform: UNKNOWN
Classifier: Programming Language :: Python :: 3
Classifier: License :: OSI Approved :: MIT License
Classifier: Operating System :: OS Independent
